ipyanimlab/__init__.py
ipyanimlab/animation.py
ipyanimlab/asset.py
ipyanimlab/bvh.py
ipyanimlab/fbxreader.py
ipyanimlab/procedural_asset.py
ipyanimlab/timeline.py
ipyanimlab/utils.py
ipyanimlab/viewer.py
ipyanimlab/assets/AnimLabSimpleMale.fbx
ipyanimlab/assets/AnimLabSimpleMale.usd
ipyanimlab/assets/ShaderBall.usd
ipyanimlab/assets/__init__.py
ipyanimlab/assets/cube.usd
ipyanimlab/assets/sphere.usd
ipyanimlab/render/__init__.py
ipyanimlab/render/axis.py
ipyanimlab/render/background.py
ipyanimlab/render/frustum.py
ipyanimlab/render/gbuffer.py
ipyanimlab/render/ground.py
ipyanimlab/render/line.py
ipyanimlab/render/material.py
ipyanimlab/render/mesh.py
ipyanimlab/render/mesh_render.py
ipyanimlab/render/screen_vbo.py
ipyanimlab/render/shadow.py
ipyanimlab/render/show_texture.py
ipyanimlab/render/sky.py
ipyanimlab/render/ssao.py
ipyanimlab/usd/__init__.py
ipyanimlab/usd/import_animation.py
ipyanimlab/usd/import_asset.py
ipyanimlab/usd/material_prim.py
ipyanimlab/usd/reading_accessors.py
ipyanimlab/usd/reading_buffers.py
ipyanimlab/usd/reading_mesh.py
ipyanimlab/usd/rigid_asset.py
ipyanimlab/usd/skeleton_prim.py
ipyanimlab/usd/skinned_asset.py
ipyanimlab-1.2.1.dist-info/METADATA
ipyanimlab-1.2.1.dist-info/WHEEL
ipyanimlab-1.2.1.dist-info/licenses/LICENSE.txt
ipyanimlab-1.2.1.dist-info/RECORD
