Metadata-Version: 2.4
Name: ipyanimlab
Version: 1.2.1
Summary: An Animation R&D jupyter Lab, build on top of ipywebgl
Project-URL: Homepage, https://github.com/JeromeEippers/ipyanimlab
Project-URL: Documentation, https://ipyanimlab.readthedocs.io/en/latest/index.html
Author-email: Jerome Eippers <jerome@eippers.be>
License: Copyright (c) 2024 Jerome Eippers
License-File: LICENSE.txt
Keywords: IPython,Jupyter,WebGl,Widgets
Classifier: Framework :: Jupyter
Classifier: Intended Audience :: Developers
Classifier: Intended Audience :: Science/Research
Classifier: Programming Language :: Python :: 3
Requires-Python: >=3.7
Requires-Dist: ipywebgl
Requires-Dist: numpy
Requires-Dist: usd-core
